ertk/__init__.py
ertk/classification.py
ertk/config.py
ertk/metrics.py
ertk/stats.py
ertk/train.py
ertk/transform.py
ertk/cli/__init__.py
ertk/cli/_utils.py
ertk/cli/cli/__init__.py
ertk/cli/cli/__main__.py
ertk/cli/cli/classify.py
ertk/cli/cli/exp.py
ertk/cli/cli/exp2.py
ertk/cli/cli/train.py
ertk/cli/dataset/__init__.py
ertk/cli/dataset/__main__.py
ertk/cli/dataset/annotation_stats.py
ertk/cli/dataset/combine.py
ertk/cli/dataset/convert.py
ertk/cli/dataset/filter_clips.py
ertk/cli/dataset/info.py
ertk/cli/dataset/process.py
ertk/cli/dataset/remove_instances.py
ertk/cli/dataset/setup.py
ertk/cli/dataset/vis.py
ertk/cli/util/__init__.py
ertk/cli/util/__main__.py
ertk/cli/util/convert_audeep.py
ertk/cli/util/create_cv_dirs.py
ertk/cli/util/names_to_filenames.py
ertk/cli/util/parallel_jobs.py
ertk/cli/util/pgrid_to_confs.py
ertk/cli/util/split_chat.py
ertk/cli/util/split_elan.py
ertk/dataset/__init__.py
ertk/dataset/annotation.py
ertk/dataset/dataset.py
ertk/dataset/features.py
ertk/dataset/utils.py
ertk/dataset/predefined/README.md
ertk/dataset/predefined/__init__.py
ertk/dataset/predefined/AESDD/corpus.yaml
ertk/dataset/predefined/AESDD/process.py
ertk/dataset/predefined/ASED/corpus.yaml
ertk/dataset/predefined/ASED/process.py
ertk/dataset/predefined/BAVED/corpus.yaml
ertk/dataset/predefined/BAVED/process.py
ertk/dataset/predefined/CMU-MOSEI/corpus.yaml
ertk/dataset/predefined/CMU-MOSEI/process.py
ertk/dataset/predefined/CREMA-D/corpus.yaml
ertk/dataset/predefined/CREMA-D/process.py
ertk/dataset/predefined/CaFE/corpus.yaml
ertk/dataset/predefined/CaFE/process.py
ertk/dataset/predefined/DEMoS/corpus.yaml
ertk/dataset/predefined/DEMoS/process.py
ertk/dataset/predefined/EESC/corpus.yaml
ertk/dataset/predefined/EESC/process.py
ertk/dataset/predefined/EMO-DB/corpus.yaml
ertk/dataset/predefined/EMO-DB/process.py
ertk/dataset/predefined/EMOVO/corpus.yaml
ertk/dataset/predefined/EMOVO/process.py
ertk/dataset/predefined/ESD/corpus.yaml
ertk/dataset/predefined/ESD/process.py
ertk-2024.4.0.dist-info/LICENSE
ertk-2024.4.0.dist-info/METADATA
ertk-2024.4.0.dist-info/WHEEL
ertk-2024.4.0.dist-info/entry_points.txt
ertk-2024.4.0.dist-info/top_level.txt
ertk-2024.4.0.dist-info/RECORD
