Metadata-Version: 2.1
Name: ertk
Version: 2024.4.0
Summary: Tools for process emotion recognition datasets, extracting features, and running experiments.
Home-page: https://github.com/Strong-AI-Lab/emotion
Author: Aaron Keesing
Author-email: akee511@aucklanduni.ac.nz
License: MIT
Classifier: Development Status :: 3 - Alpha
Classifier: Environment :: Console
Classifier: Environment :: GPU :: NVIDIA CUDA
Classifier: Intended Audience :: Developers
Classifier: Intended Audience :: Science/Research
Classifier: License :: OSI Approved :: MIT License
Classifier: Natural Language :: English
Classifier: Operating System :: OS Independent
Classifier: Programming Language :: Python :: 3 :: Only
Classifier: Programming Language :: Python :: 3.8
Classifier: Programming Language :: Python :: 3.9
Classifier: Programming Language :: Python :: 3.10
Classifier: Programming Language :: Python :: 3.11
Classifier: Topic :: Multimedia :: Sound/Audio :: Analysis
Classifier: Topic :: Multimedia :: Sound/Audio :: Speech
Classifier: Topic :: Scientific/Engineering
Classifier: Topic :: Software Development
Requires-Python: >=3.8
License-File: LICENSE
Requires-Dist: click>=8.0.0
Requires-Dist: click-option-group
Requires-Dist: importlib-metadata
Requires-Dist: importlib-resources
Requires-Dist: joblib
Requires-Dist: keras
Requires-Dist: liac-arff
Requires-Dist: liblinear-official
Requires-Dist: librosa
Requires-Dist: matplotlib>=3.0.0
Requires-Dist: netCDF4
Requires-Dist: numpy
Requires-Dist: omegaconf>=2.1
Requires-Dist: pandas>=1.4.0
Requires-Dist: pytorch-lightning
Requires-Dist: seaborn
Requires-Dist: scikit-learn
Requires-Dist: scipy
Requires-Dist: soundfile
Requires-Dist: statsmodels
Requires-Dist: tensorflow>=2.3.0
Requires-Dist: torch
Requires-Dist: torchaudio
Requires-Dist: tqdm
Provides-Extra: all-preprocessors
Requires-Dist: tensorflow-hub; extra == "all-preprocessors"
Requires-Dist: encodec; extra == "all-preprocessors"
Requires-Dist: opensmile>=2.4.0; extra == "all-preprocessors"
Requires-Dist: phonemizer; extra == "all-preprocessors"
Requires-Dist: transformers; extra == "all-preprocessors"
Requires-Dist: keras-applications; extra == "all-preprocessors"
Requires-Dist: keras-preprocessing; extra == "all-preprocessors"
Requires-Dist: speechbrain<1.0.0; extra == "all-preprocessors"
Requires-Dist: resampy>=0.4.0; extra == "all-preprocessors"
Provides-Extra: audioset
Requires-Dist: tensorflow-hub; extra == "audioset"
Provides-Extra: encodec
Requires-Dist: encodec; extra == "encodec"
Provides-Extra: huggingface
Requires-Dist: transformers; extra == "huggingface"
Provides-Extra: keras_apps
Requires-Dist: keras-applications; extra == "keras-apps"
Requires-Dist: keras-preprocessing; extra == "keras-apps"
Provides-Extra: opensmile
Requires-Dist: opensmile>=2.4.0; extra == "opensmile"
Provides-Extra: phonemize
Requires-Dist: phonemizer; extra == "phonemize"
Provides-Extra: resample
Requires-Dist: resampy>=0.4.0; extra == "resample"
Provides-Extra: speechbrain
Requires-Dist: speechbrain<1.0.0; extra == "speechbrain"
